repoze.debug-1.1-py2.7-nspkg.pth
repoze/debug/__init__.py
repoze/debug/_compat.py
repoze/debug/canary.py
repoze/debug/pdbpm.py
repoze/debug/responselogger.py
repoze/debug/states.txt
repoze/debug/threads.py
repoze/debug/ui.py
repoze/debug/scripts/__init__.py
repoze/debug/scripts/requestprofiler.py
repoze/debug/scripts/tests/__init__.py
repoze/debug/scripts/tests/test_requestprofiler.py
repoze/debug/static/debugui-entryviewer.xsl
repoze/debug/static/debugui-html.css
repoze/debug/static/debugui-html.js
repoze/debug/static/debugui-html.xsl
repoze/debug/static/debugui-shared.css
repoze/debug/static/debugui-shared.js
repoze/debug/static/debugui-xul.css
repoze/debug/static/debugui-xul.js
repoze/debug/static/debugui-xul.xsl
repoze/debug/static/debugui.html
repoze/debug/static/debugui.xul
repoze/debug/static/samplefeed.xml
repoze/debug/static/samplelogentries.xml
repoze/debug/static/sarissa.js
repoze/debug/static/xmlverbatim.xsl
repoze/debug/tests/__init__.py
repoze/debug/tests/test_canary.py
repoze/debug/tests/test_pdbpm.py
repoze/debug/tests/test_responselogger.py
repoze/debug/tests/test_threads.py
repoze/debug/tests/test_ui.py
repoze.debug-1.1.dist-info/DESCRIPTION.rst
repoze.debug-1.1.dist-info/METADATA
repoze.debug-1.1.dist-info/RECORD
repoze.debug-1.1.dist-info/WHEEL
repoze.debug-1.1.dist-info/entry_points.txt
repoze.debug-1.1.dist-info/metadata.json
repoze.debug-1.1.dist-info/namespace_packages.txt
repoze.debug-1.1.dist-info/top_level.txt
