Metadata-Version: 2.0
Name: repoze.debug
Version: 1.1
Summary: Forensic debugging WSGI middleware
Home-page: http://www.repoze.org
Author: Agendaless Consulting
Author-email: repoze-dev@lists.repoze.org
License: BSD-derived (http://www.repoze.org/LICENSE.txt)
Keywords: wsgi request response debug middleware
Platform: UNKNOWN
Classifier: Development Status :: 5 - Production/Stable
Classifier: Intended Audience :: Developers
Classifier: Programming Language :: Python
Classifier: Programming Language :: Python :: 2
Classifier: Programming Language :: Python :: 2.7
Classifier: Programming Language :: Python :: 3
Classifier: Programming Language :: Python :: 3.3
Classifier: Programming Language :: Python :: 3.4
Classifier: Programming Language :: Python :: 3.5
Classifier: Programming Language :: Python :: Implementation :: CPython
Classifier: Programming Language :: Python :: Implementation :: PyPy
Classifier: Topic :: Internet :: WWW/HTTP
Classifier: Topic :: Internet :: WWW/HTTP :: Dynamic Content
Classifier: Topic :: Internet :: WWW/HTTP :: WSGI
Classifier: Topic :: Internet :: WWW/HTTP :: WSGI :: Middleware
Requires-Dist: WebOb
Provides-Extra: docs
Requires-Dist: Sphinx; extra == 'docs'
Requires-Dist: WebOb; extra == 'docs'
Provides-Extra: testing
Requires-Dist: WebOb; extra == 'testing'
Requires-Dist: coverage; extra == 'testing'
Requires-Dist: nose; extra == 'testing'
